Sunshine/__init__.py
Sunshine/messages.py
Sunshine/moonlight.py
Sunshine/sunshine.py
SunshineDB-1.5.dist-info/METADATA
SunshineDB-1.5.dist-info/WHEEL
SunshineDB-1.5.dist-info/top_level.txt
SunshineDB-1.5.dist-info/RECORD
