Metadata-Version: 2.1
Name: SunshineDB
Version: 1.5
Summary: Lightweight json-database library for Python
Home-page: https://github.com/Sunshine-Database/Sunshine
Author: de4oult
Author-email: kayra.dist@email.com
License: MIT License
Keywords: sunshine,database,json,json-database,db,async
Requires-Python: >=3
Requires-Dist: colorama
Requires-Dist: filelock
